CurrenTime/CurrenTime.py
CurrenTime/__init__.py
currentime-1.0.3.dist-info/METADATA
currentime-1.0.3.dist-info/WHEEL
currentime-1.0.3.dist-info/licenses/LICENSE
currentime-1.0.3.dist-info/RECORD
