Metadata-Version: 2.1
Name: CurrenTime
Version: 1.0.3
Summary: A small and simple package to get current Date and Time
Project-URL: GitHub, https://github.com/NotScottt/CurrenTime
Author-email: Scott Zachariae <scott.zachariae@outlook.com>
License-File: LICENSE
Classifier: License :: OSI Approved :: MIT License
Classifier: Operating System :: OS Independent
Classifier: Programming Language :: Python :: 3
Requires-Python: >=3.7
